Workbook
Name aporte: Cenario!$D$19
Name patrimonio: Cenario!$D$22
Name qtd_anos: Cenario!$D$20
Name rendimento_carteira: Cenario!$D$15
Name salario: Cenario!$D$14
Name sugestao_investimento: Cenario!$D$16
Name taxa_mensal: Cenario!$D$21

Sheet Cenario
B13: CONFIGURAÇÕES
B14: Salário | D14: 6000
B15: Rendimento Carteira | D15: 0.006
B16: Sugestão de Investimento(30%) | D16: =D14*30% -> 1800
B18: INVESTIMENTO MENSAL
B19: Quanto investir por mês? | D19: 1800
B20: Por Quantos Anos? | D20: 5
B21: Taxa de Rendimeto mensal? | D21: 0.01079
B22: Patrimônio acumulado? | D22: =FV(taxa_mensal,qtd_anos*12,aporte)*-1 -> 150798.45
B23: Dividendos Mensais? | D23: =patrimonio*rendimento_carteira -> 904.79067
B25: Cenários | D25: Dividendo
A26: 2 | B26: Quanto em 2 Anos? | C26: =FV($D$21,$A26*12,$D$19*-1) -> 49009.729 | D26: =C26*rendimento_carteira -> 294.05837
A27: 7 | B27: Quanto em 7 Anos? | C27: =FV($D$21,$A27*12,$D$19*-1) -> 244110.66 | D27: =C27*rendimento_carteira -> 1464.664
A28: 10 | B28: Quanto em 10 Anos? | C28: =FV($D$21,$A28*12,$D$19*-1) -> 437911.58 | D28: =C28*rendimento_carteira -> 2627.4695
A29: 20 | B29: Quanto em 20 Anos? | C29: =FV($D$21,$A29*12,$D$19*-1) -> 2025357.1 | D29: =C29*rendimento_carteira -> 12152.143
A30: 30 | B30: Quanto em 30 Anos? | C30: =FV($D$21,$A30*12,$D$19*-1) -> 7779905.4 | D30: =C30*rendimento_carteira -> 46679.432
B32: PERFIL | C32: Moderado
B33: VALOR A SER INVESTIDO POR MÊS | C33: =aporte -> 1800
B35: TIPO DE FII | C35: % Sugerido | D35: Valores
B36: PAPEL | C36: =VLOOKUP($C$32&"-"&B36,Planilha2!$A:$D,4,FALSE) -> 0.32 | D36: =C36*$C$33 -> 576
B37: TIJOLO | C37: =VLOOKUP($C$32&"-"&B37,Planilha2!$A:$D,4,FALSE) -> 0.35 | D37: =C37*$C$33 -> 630
B38: HÍBRIDOS | C38: =VLOOKUP($C$32&"-"&B38,Planilha2!$A:$D,4,FALSE) -> 0.08 | D38: =C38*$C$33 -> 144
B39: Fof's | C39: =VLOOKUP($C$32&"-"&B39,Planilha2!$A:$D,4,FALSE) -> 0.05 | D39: =C39*$C$33 -> 90
B40: DESENVOLVIMENTO | C40: =VLOOKUP($C$32&"-"&B40,Planilha2!$A:$D,4,FALSE) -> 0.1 | D40: =C40*$C$33 -> 180
B41: HOTELARIAS | C41: =VLOOKUP($C$32&"-"&B41,Planilha2!$A:$D,4,FALSE) -> 0.1 | D41: =C41*$C$33 -> 180
D42: =SUM(D36:D41) -> 1800

Sheet Planilha2
A2: CHAVE | B2: PERFIL | C2: TIPO DE FII | D2: %
A3: =B3&"-"&C3 -> Conservardor-PAPEL | B3: Conservardor | C3: PAPEL | D3: 0.3
A4: =B4&"-"&C4 -> Conservardor-TIJOLO | B4: Conservardor | C4: TIJOLO | D4: 0.5
A5: =B5&"-"&C5 -> Conservardor-HÍBRIDOS | B5: Conservardor | C5: HÍBRIDOS | D5: 0.1
A6: =B6&"-"&C6 -> Conservardor-Fof's | B6: Conservardor | C6: Fof's | D6: 0.1
A7: =B7&"-"&C7 -> Conservardor-DESENVOLVIMENTO | B7: Conservardor | C7: DESENVOLVIMENTO | D7: 0
A8: =B8&"-"&C8 -> Conservardor-HOTELARIAS | B8: Conservardor | C8: HOTELARIAS | D8: 0
A9: =B9&"-"&C9 -> Moderado-PAPEL | B9: Moderado | C9: PAPEL | D9: 0.32
A10: =B10&"-"&C10 -> Moderado-TIJOLO | B10: Moderado | C10: TIJOLO | D10: 0.35
A11: =B11&"-"&C11 -> Moderado-HÍBRIDOS | B11: Moderado | C11: HÍBRIDOS | D11: 0.08
A12: =B12&"-"&C12 -> Moderado-Fof's | B12: Moderado | C12: Fof's | D12: 0.05
A13: =B13&"-"&C13 -> Moderado-DESENVOLVIMENTO | B13: Moderado | C13: DESENVOLVIMENTO | D13: 0.1
A14: =B14&"-"&C14 -> Moderado-HOTELARIAS | B14: Moderado | C14: HOTELARIAS | D14: 0.1
... A20: =B20&"-"&C20 -> Agressivo-HOTELARIAS | B20: Agressivo | C20: HOTELARIAS | D20: 0.1
